{"cameraMode":{"drawMode":0,"name":"Shaded","section":"Shading Mode"},"sceneLighting":true,"audioPlay":false,"sceneViewState":{"m_AlwaysRefresh":false,"showFog":true,"showSkybox":true,"showFlares":true,"showImageEffects":true,"showParticleSystems":true,"showVisualEffectGraphs":true,"m_FxEnabled":true},"in2DMode":false,"pivot":{"x":27.10009765625,"y":-58.57000732421875,"z":62.988494873046878},"rotation":{"x":0.27101001143455508,"y":0.2956094741821289,"z":-0.08785902708768845,"w":0.9118373394012451},"size":152.4833526611328,"orthographic":false}